lame_helpers_for_opencv_on_vscode/__init__.py
lame_helpers_for_opencv_on_vscode/main.py
lame_helpers_for_opencv_on_vscode-0.0.10.dist-info/LICENSE.txt
lame_helpers_for_opencv_on_vscode-0.0.10.dist-info/METADATA
lame_helpers_for_opencv_on_vscode-0.0.10.dist-info/WHEEL
lame_helpers_for_opencv_on_vscode-0.0.10.dist-info/top_level.txt
lame_helpers_for_opencv_on_vscode-0.0.10.dist-info/RECORD
